Metadata-Version: 1.0
Name: submitter
Version: 0.4
Summary: Simple SGE job submitter.
Home-page: https://github.com/BillyLiggins/Submitter
Author: Billy Liggins
Author-email: billyliggins@gmail.com
License: MIT
Platform: UNKNOWN
